mitmproxy_escher/__init__.py
mitmproxy_escher/__main__.py
mitmproxy_escher/test.py
mitmproxy_escher-5.0.0.dist-info/LICENSE
mitmproxy_escher-5.0.0.dist-info/METADATA
mitmproxy_escher-5.0.0.dist-info/WHEEL
mitmproxy_escher-5.0.0.dist-info/top_level.txt
mitmproxy_escher-5.0.0.dist-info/zip-safe
mitmproxy_escher-5.0.0.dist-info/RECORD
