Metadata-Version: 2.1
Name: mitmproxy-escher
Version: 5.0.0
Summary: Sign mitmproxy requests with Escher
Home-page: https://github.com/knagy/mitmproxy-escher
Author: Nagy Krisztián
Author-email: knagy@deadlime.hu
License: MIT
Classifier: License :: OSI Approved :: MIT License
Classifier: Environment :: Console
Classifier: Programming Language :: Python
Classifier: Programming Language :: Python :: 3
Classifier: Programming Language :: Python :: 3 :: Only
Classifier: Topic :: Security
Classifier: Topic :: Internet
Classifier: Topic :: Internet :: WWW/HTTP
Classifier: Topic :: Internet :: Proxy Servers
License-File: LICENSE
Requires-Dist: escherauth<2.0,>=1.0.3
Requires-Dist: mitmproxy<12.0.0,>=9.0.0
